odoo/addons/sale_partner_approval/README.rst
odoo/addons/sale_partner_approval/__init__.py
odoo/addons/sale_partner_approval/__manifest__.py
odoo/addons/sale_partner_approval/data/exception_rule.xml
odoo/addons/sale_partner_approval/data/init_sale_ok.xml
odoo/addons/sale_partner_approval/i18n/sale_partner_approval.pot
odoo/addons/sale_partner_approval/models/__init__.py
odoo/addons/sale_partner_approval/models/res_partner.py
odoo/addons/sale_partner_approval/models/res_partner_stage.py
odoo/addons/sale_partner_approval/models/sale_order.py
odoo/addons/sale_partner_approval/readme/CONFIGURE.rst
odoo/addons/sale_partner_approval/readme/CONTRIBUTORS.rst
odoo/addons/sale_partner_approval/readme/DESCRIPTION.rst
odoo/addons/sale_partner_approval/readme/USAGE.rst
odoo/addons/sale_partner_approval/static/description/icon.png
odoo/addons/sale_partner_approval/static/description/index.html
odoo/addons/sale_partner_approval/tests/__init__.py
odoo/addons/sale_partner_approval/tests/test_product_approval.py
odoo/addons/sale_partner_approval/views/res_partner.xml
odoo/addons/sale_partner_approval/views/res_partner_stage.xml
odoo14_addon_sale_partner_approval-14.0.2.0.0.dist-info/METADATA
odoo14_addon_sale_partner_approval-14.0.2.0.0.dist-info/WHEEL
odoo14_addon_sale_partner_approval-14.0.2.0.0.dist-info/top_level.txt
odoo14_addon_sale_partner_approval-14.0.2.0.0.dist-info/RECORD
