Metadata-Version: 2.1
Name: odoo14-addon-sale-partner-approval
Version: 14.0.2.0.0
Summary: Control Partners that can be used in Sales Orders
Home-page: https://github.com/OCA/sale-workflow
Author: Open Source Integrators, Odoo Community Association (OCA)
Author-email: support@odoo-community.org
License: AGPL-3
Platform: UNKNOWN
Classifier: Programming Language :: Python
Classifier: Framework :: Odoo
Classifier: Framework :: Odoo :: 14.0
Classifier: License :: OSI Approved :: GNU Affero General Public License v3
Classifier: Development Status :: 3 - Alpha
Requires-Python: >=3.6
Requires-Dist: odoo14-addon-partner-stage
Requires-Dist: odoo14-addon-sale-exception
Requires-Dist: odoo (<14.1dev,>=14.0a)
